cloud_instance/__init__.py
cloud_instance/cli/cli.py
cloud_instance/cli/dep.py
cloud_instance/models/create.py
cloud_instance/models/delete.py
cloud_instance/models/gather.py
cloud_instance/models/modify.py
cloud_instance/models/resize.py
cloud_instance/models/slated.py
cloud_instance/util/build.py
cloud_instance/util/common.py
cloud_instance/util/fetch.py
cloud_instance/util/parse.py
cloud_instance/util/provision.py
cloud_instance/util/terminate.py
cloud_instance-0.1.6.dist-info/LICENSE
cloud_instance-0.1.6.dist-info/METADATA
cloud_instance-0.1.6.dist-info/WHEEL
cloud_instance-0.1.6.dist-info/entry_points.txt
cloud_instance-0.1.6.dist-info/RECORD
